fib_o_na_cci_ser_ies.py
fib_o_na_cci_ser_ies-1.0.dist-info/METADATA
fib_o_na_cci_ser_ies-1.0.dist-info/WHEEL
fib_o_na_cci_ser_ies-1.0.dist-info/top_level.txt
fib_o_na_cci_ser_ies-1.0.dist-info/RECORD
