Metadata-Version: 2.1
Name: fib-o-na-cci-ser-ies
Version: 1.0
Summary: To find the fibbonacci series for a given range
Home-page: https://github.com/Anumesh01/fib_o_na_cci_ser_ies
Author: ANUMESH R
Author-email: anumesh0124@gmail.com
License: UNKNOWN
Platform: UNKNOWN
Classifier: Programming Language :: Python :: 3.5
Classifier: Programming Language :: Python :: 3.6
Classifier: Programming Language :: Python :: 3.7
Classifier: Programming Language :: Python :: 3.8
Classifier: Operating System :: OS Independent
